[1,["55NPpWqJBBaYIWqcZHE3RA","b6ibsEB4lCQLwTOjOITE/8@f9941","a7GOUVWLNAtZDt37JO1oCd@f9941","0evKif+qhI4a0nWnGerFTr@6c48a","62fiE42RdII40awyhjvEjV@6c48a","a7GOUVWLNAtZDt37JO1oCd@6c48a","b6ibsEB4lCQLwTOjOITE/8@6c48a","bdBtwdI99M2rQQLUWJx4cH@6c48a","c6zKmSR15HMJ8mbEkQ1g2N@6c48a","e4Ra1Gg/xMZ58oM066fxdB@6c48a","bdBtwdI99M2rQQLUWJx4cH@f9941","62fiE42RdII40awyhjvEjV@f9941","e4Ra1Gg/xMZ58oM066fxdB@f9941","0evKif+qhI4a0nWnGerFTr@f9941","c6zKmSR15HMJ8mbEkQ1g2N@f9941"],["node","_spriteFrame","_textureSource","_font","_target","_normalSprite","root","secondNode","firstNode","data","_parent"],["cc.SpriteFrame",["cc.Node",["_name","_layer","_active","_objFlags","_components","_prefab","_parent","_children","_lpos"],-1,9,4,1,2,5],["cc.UITransform",["node","__prefab","_contentSize","_anchorPoint"],3,1,4,5,5],["cc.Label",["_string","_actualFontSize","_fontSize","_isSystemFontUsed","_overflow","_enableWrapText","_horizontalAlign","node","__prefab","_font"],-4,1,4,6],["cc.Sprite",["_type","_sizeMode","node","__prefab","_spriteFrame"],1,1,4,6],["cc.Prefab",["_name"],2],["cc.CompPrefabInfo",["fileId"],2],["cc.Widget",["_alignFlags","_originalWidth","_originalHeight","node","__prefab"],0,1,4],["720eaaGjSxOgYZBxX7eU+UB",["node","__prefab","firstNode","secondNode"],3,1,4,1,1],["cc.PrefabInfo",["fileId","instance","targetOverrides","nestedPrefabInstanceRoots","root","asset"],-1,1,1],["cc.Button",["_transition","node","__prefab","clickEvents","_normalColor","_target","_normalSprite"],2,1,4,9,5,1,6],["cc.ClickEvent",["_componentId","handler","target"],1,1],["cc.LabelOutline",["_width","node","__prefab","_color"],2,1,4,5]],[[6,0,2],[9,0,1,2,3,4,5,5],[2,0,1,2,1],[1,0,1,6,4,5,8,3],[12,0,1,2,3,2],[4,0,1,2,3,4,3],[1,0,1,6,7,4,5,8,3],[4,2,3,4,1],[2,0,1,2,3,1],[3,0,1,2,3,7,8,9,5],[1,0,1,6,7,4,5,3],[1,0,3,1,6,4,5,8,4],[2,0,1,1],[7,0,1,2,3,4,4],[10,0,1,2,3,4,5,6,2],[11,0,1,2,3],[3,0,1,2,4,5,3,7,8,9,7],[3,0,6,1,2,3,7,8,9,6],[5,0,2],[1,0,1,7,4,5,3],[1,0,2,1,7,4,5,4],[1,0,1,6,4,5,3],[8,0,1,2,3,1]],[[[{"name":"icon_2","rect":{"x":0,"y":5,"width":90,"height":80},"offset":{"x":0,"y":0},"originalSize":{"width":90,"height":90},"rotated":false,"capInsets":[0,0,0,0],"vertices":{"rawPosition":[-45,-40,0,45,-40,0,-45,40,0,45,40,0],"indexes":[0,1,2,2,1,3],"uv":[0,85,90,85,0,5,90,5],"nuv":[0,0.05555555555555555,1,0.05555555555555555,0,0.9444444444444444,1,0.9444444444444444],"minPos":{"x":-45,"y":-40,"z":0},"maxPos":{"x":45,"y":40,"z":0}},"packable":true,"pixelsToUnit":100,"pivot":{"x":0.5,"y":0.5},"meshType":0}],[0],0,[0],[2],[3]],[[{"name":"bg_1","rect":{"x":0,"y":0,"width":470,"height":320},"offset":{"x":0,"y":0},"originalSize":{"width":470,"height":320},"rotated":false,"capInsets":[0,0,0,0],"vertices":{"rawPosition":[-235,-160,0,235,-160,0,-235,160,0,235,160,0],"indexes":[0,1,2,2,1,3],"uv":[0,320,470,320,0,0,470,0],"nuv":[0,0,1,0,0,1,1,1],"minPos":{"x":-235,"y":-160,"z":0},"maxPos":{"x":235,"y":160,"z":0}},"packable":true,"pixelsToUnit":100,"pivot":{"x":0.5,"y":0.5},"meshType":0}],[0],0,[0],[2],[4]],[[{"name":"content_bg2","rect":{"x":0,"y":0,"width":44,"height":44},"offset":{"x":0,"y":0},"originalSize":{"width":44,"height":44},"rotated":false,"capInsets":[20,20,20,20],"vertices":{"rawPosition":[-22,-22,0,22,-22,0,-22,22,0,22,22,0],"indexes":[0,1,2,2,1,3],"uv":[0,44,44,44,0,0,44,0],"nuv":[0,0,1,0,0,1,1,1],"minPos":{"x":-22,"y":-22,"z":0},"maxPos":{"x":22,"y":22,"z":0}},"packable":true,"pixelsToUnit":100,"pivot":{"x":0.5,"y":0.5},"meshType":0}],[0],0,[0],[2],[5]],[[{"name":"btn_gree","rect":{"x":0,"y":0,"width":63,"height":90},"offset":{"x":0,"y":0},"originalSize":{"width":63,"height":90},"rotated":false,"capInsets":[33,0,30,0],"vertices":{"rawPosition":[-31.5,-45,0,31.5,-45,0,-31.5,45,0,31.5,45,0],"indexes":[0,1,2,2,1,3],"uv":[0,90,63,90,0,0,63,0],"nuv":[0,0,1,0,0,1,1,1],"minPos":{"x":-31.5,"y":-45,"z":0},"maxPos":{"x":31.5,"y":45,"z":0}},"packable":true,"pixelsToUnit":100,"pivot":{"x":0.5,"y":0.5},"meshType":0}],[0],0,[0],[2],[6]],[[{"name":"window_bg1","rect":{"x":0,"y":0,"width":90,"height":116},"offset":{"x":0,"y":0},"originalSize":{"width":90,"height":116},"rotated":false,"capInsets":[38,70,38,43],"vertices":{"rawPosition":[-45,-58,0,45,-58,0,-45,58,0,45,58,0],"indexes":[0,1,2,2,1,3],"uv":[0,116,90,116,0,0,90,0],"nuv":[0,0,1,0,0,1,1,1],"minPos":{"x":-45,"y":-58,"z":0},"maxPos":{"x":45,"y":58,"z":0}},"packable":true,"pixelsToUnit":100,"pivot":{"x":0.5,"y":0.5},"meshType":0}],[0],0,[0],[2],[7]],[[{"name":"icon_3","rect":{"x":7,"y":10,"width":76,"height":72},"offset":{"x":0,"y":-1},"originalSize":{"width":90,"height":90},"rotated":false,"capInsets":[0,0,0,0],"vertices":{"rawPosition":[-38,-36,0,38,-36,0,-38,36,0,38,36,0],"indexes":[0,1,2,2,1,3],"uv":[7,80,83,80,7,8,83,8],"nuv":[0.07777777777777778,0.08888888888888889,0.9222222222222223,0.08888888888888889,0.07777777777777778,0.8888888888888888,0.9222222222222223,0.8888888888888888],"minPos":{"x":-38,"y":-36,"z":0},"maxPos":{"x":38,"y":36,"z":0}},"packable":true,"pixelsToUnit":100,"pivot":{"x":0.5,"y":0.5},"meshType":0}],[0],0,[0],[2],[8]],[[{"name":"icon_1","rect":{"x":5,"y":3,"width":83,"height":85},"offset":{"x":1.5,"y":-0.5},"originalSize":{"width":90,"height":90},"rotated":false,"capInsets":[0,0,0,0],"vertices":{"rawPosition":[-41.5,-42.5,0,41.5,-42.5,0,-41.5,42.5,0,41.5,42.5,0],"indexes":[0,1,2,2,1,3],"uv":[5,87,88,87,5,2,88,2],"nuv":[0.05555555555555555,0.022222222222222223,0.9777777777777777,0.022222222222222223,0.05555555555555555,0.9666666666666667,0.9777777777777777,0.9666666666666667],"minPos":{"x":-41.5,"y":-42.5,"z":0},"maxPos":{"x":41.5,"y":42.5,"z":0}},"packable":true,"pixelsToUnit":100,"pivot":{"x":0.5,"y":0.5},"meshType":0}],[0],0,[0],[2],[9]],[[[18,"mine_help_window"],[19,"mine_help_window",33554432,[-7,-8],[[2,-2,[0,"91/H87rq1Dop0aK4Y4u48f"],[5,720,1280]],[13,45,100,800,-3,[0,"5bRizDhl1JUaTQ9+LYibZl"]],[22,-6,[0,"09W+uDmBpKm7wy4lmGu8wb"],-5,-4]],[1,"76nHfr96ZHxo0iVoIAn6T2",null,null,null,-1,0]],[20,"second",false,33554432,[-10,-11,-12,-13],[[12,-9,[0,"9fwRD240pJL4nsdBMj04zV"]]],[1,"28ooAlePNHaZklFA759E3o",null,null,null,1,0]],[10,"win_node",33554432,1,[-16,-17,2],[[2,-14,[0,"17RHl7641PArJaLqTk/tqv"],[5,720,1280]],[13,45,200,249.525,-15,[0,"3f1fYt8aFIMpDhMU1RTz3T"]]],[1,"bavqaWN2VFuY7LrCiQBp0k",null,null,null,1,0]],[10,"first",33554432,3,[-19,-20,-21],[[12,-18,[0,"42EFnr4V5GIIlTnh7aV60h"]]],[1,"9bLzCaX5dGXrcgTNNZGFQz",null,null,null,1,0]],[6,"btn:but",33554432,4,[-26],[[2,-22,[0,"eaZ1BNao5IkKyEFQ80CG91"],[5,216,90]],[5,1,0,-23,[0,"75XlmM9GRLkbEZNczcKgcC"],4],[14,3,-25,[0,"47NQSlfOBM3phsMQeR6atc"],[[15,"720eaaGjSxOgYZBxX7eU+UB","onClickFirst",1]],[4,4292269782],-24,5]],[1,"076ATFu4REW6WHmY7gn5QV",null,null,null,1,0],[1,0,-223,0]],[6,"btn:but",33554432,2,[-31],[[2,-27,[0,"c7fNU0u/BL+YvFdIU/iPPd"],[5,216,90]],[5,1,0,-28,[0,"7eRBf3JhNJ8onoypVe1lPk"],16],[14,3,-30,[0,"8cXe1QGc9E1LFGiY4Vl0GC"],[[15,"720eaaGjSxOgYZBxX7eU+UB","onClickSecond",1]],[4,4292269782],-29,17]],[1,"26asZ3ijtD4bPTpYlDHqDg",null,null,null,1,0],[1,0,-223,0]],[6,"content_bg2",33554432,2,[-34,-35],[[2,-32,[0,"2aWkNcschOwJ8xI3hKVwTO"],[5,470,117]],[5,1,0,-33,[0,"54tGGsxyJNO5JUqxvpeGHT"],8]],[1,"bbit0Da1FPBY/dXY4GWEIQ",null,null,null,1,0],[1,0,166,0]],[6,"content_bg3",33554432,2,[-38,-39],[[2,-36,[0,"37443MzWdGAopvJMm0LRwg"],[5,470,117]],[5,1,0,-37,[0,"72g6okQFlJ0ZBmvrPo1a1f"],11]],[1,"848EUSH8pAzK1xsGeImR3Q",null,null,null,1,0],[1,0,32,0]],[6,"content_bg4",33554432,2,[-42,-43],[[2,-40,[0,"e9Sj9a4QRAm5dP+J6lAmCw"],[5,470,117]],[5,1,0,-41,[0,"683zQXxoBHLqwoMnAeguzb"],14]],[1,"49bNozQ6xLaoWy9UK6isr6",null,null,null,1,0],[1,0,-102,0]],[3,"Label",33554432,4,[[2,-44,[0,"feQ9wBOYBEBJyyW0An+Owl"],[5,370,56.4]],[9,"挖黄线以下可以进入更深的地方",26,26,false,-45,[0,"55ELad/AZI9qlxFZ0ELFIP"],2],[4,3,-46,[0,"adV3xxFKFM8obW58bc7pAp"],[4,4280098342]]],[1,"60eQd2J91PNa7pIjDCtPR/",null,null,null,1,0],[1,0,-133,0]],[11,"Label",512,33554432,5,[[2,-47,[0,"6d4rc3OGlJJqVhlkkK2A0x"],[5,100,40]],[16,"下一个",26,26,1,false,false,-48,[0,"9fx7hxaGpPppmoy+uIMgtu"],3],[4,3,-49,[0,"e9qtGC9ONBR6z2PXQLkS3X"],[4,4280098342]]],[1,"19Lq829etD0r58KpZhNxIf",null,null,null,1,0],[1,0,3,0]],[3,"Label",33554432,7,[[8,-50,[0,"42+4ahdz5IL7ryE6ZMsbGQ"],[5,214,56.4],[0,0,0.5]],[9,"镐头将自动补充。",26,26,false,-51,[0,"8fOb0yi5RGip60psTITIob"],7],[4,3,-52,[0,"4ajs2cQuRLgKsU7nsC8fOM"],[4,4280098342]]],[1,"7bn5IK8CtCVa9WDe/iAnxX",null,null,null,1,0],[1,-104,0,0]],[3,"Label",33554432,8,[[8,-53,[0,"38nV0ZFwhKpa52SaPAdLie"],[5,318,96.4],[0,0,0.5]],[17,"挖的越深，越容易发现好的\n宝藏。",0,26,26,false,-54,[0,"f8rqSae1lBzIZwtNMp/9GN"],10],[4,3,-55,[0,"87SdI/gaZMK7vWGmOPzgxg"],[4,4280098342]]],[1,"565em32EtEiaQxAnLZtpis",null,null,null,1,0],[1,-104,0,0]],[3,"Label",33554432,9,[[8,-56,[0,"70ozQEZzxFDoc4CGqw0GwF"],[5,318,96.4],[0,0,0.5]],[17,"使用炸弹和钻头可以轻松破\n坏石头。",0,26,26,false,-57,[0,"49xXq5l3BIwLqLuLZOO9ez"],13],[4,3,-58,[0,"b6HnlyHPZI0JV1FweTcBUg"],[4,4280098342]]],[1,"98WndtP29BOb86Of5l6NKy",null,null,null,1,0],[1,-104,0,0]],[11,"Label",512,33554432,6,[[2,-59,[0,"23D411sChIzK8FYQ4lLStB"],[5,100,40]],[16,"确定",26,26,1,false,false,-60,[0,"44hUMYiGhCAoLTO1RpGPOu"],15],[4,3,-61,[0,"68FI4lo59ByoUrDSlJDrnb"],[4,4280098342]]],[1,"f6OqH1APBNcIDr6p3j5+nW",null,null,null,1,0],[1,0,3,0]],[3,"Label",33554432,1,[[2,-62,[0,"8aZlTyW+5Dp4EU0BTuwpjE"],[5,70,56.4]],[9,"矿山",32,32,false,-63,[0,"d5zExmkrpG6r7EOIGx1Grz"],18],[4,3,-64,[0,"8byNoFBQRG7bQ2TC/BWaY1"],[4,4282341487]]],[1,"4e1cJ3FJRFcIfNX4YC9GEZ",null,null,null,1,0],[1,0,271,0]],[21,"window_bg1",33554432,3,[[2,-65,[0,"a5avaI+x1CVoJrzLuIn42r"],[5,516,620]],[5,1,0,-66,[0,"35lkgEs3lB65H+OdqyCZIh"],0]],[1,"e1fgKj711GRr6Y2moHy08n",null,null,null,1,0]],[3,"bg_1",33554432,4,[[2,-67,[0,"f52p2Wa7tF17ixxZGYJj/J"],[5,470,320]],[7,-68,[0,"abv9t7cD5Bv471nzN0g/ey"],1]],[1,"f77GA2nPRGn68XCrMryam1",null,null,null,1,0],[1,0,65,0]],[3,"icon_1",33554432,7,[[2,-69,[0,"37PyJ40dNM/ruqNdmjFQGx"],[5,83,85]],[7,-70,[0,"f4QQqzJsxKiYOPg13MixsD"],6]],[1,"ef1yYhsZ5B9aGJ2NZG+vRR",null,null,null,1,0],[1,-167,0,0]],[3,"icon_2",33554432,8,[[2,-71,[0,"5eU0x0OTVDl4w/g5GAkHst"],[5,90,80]],[7,-72,[0,"42EjYv3wRM0YZbgQmHVAtY"],9]],[1,"18DQekPFVNyarctvZbgUj/",null,null,null,1,0],[1,-167,0,0]],[3,"icon_3",33554432,9,[[2,-73,[0,"bcFlpTnWtNc7SYKzsvGrZk"],[5,76,72]],[7,-74,[0,"26Ue918ENKL4agC/cElbRR"],12]],[1,"a6Tc7pj7dAMr/JRWl0USLQ",null,null,null,1,0],[1,-167,0,0]]],0,[0,6,1,0,0,1,0,0,1,0,7,2,0,8,4,0,0,1,0,-1,3,0,-2,16,0,0,2,0,-1,7,0,-2,8,0,-3,9,0,-4,6,0,0,3,0,0,3,0,-1,17,0,-2,4,0,0,4,0,-1,18,0,-2,10,0,-3,5,0,0,5,0,0,5,0,4,5,0,0,5,0,-1,11,0,0,6,0,0,6,0,4,6,0,0,6,0,-1,15,0,0,7,0,0,7,0,-1,19,0,-2,12,0,0,8,0,0,8,0,-1,20,0,-2,13,0,0,9,0,0,9,0,-1,21,0,-2,14,0,0,10,0,0,10,0,0,10,0,0,11,0,0,11,0,0,11,0,0,12,0,0,12,0,0,12,0,0,13,0,0,13,0,0,13,0,0,14,0,0,14,0,0,14,0,0,15,0,0,15,0,0,15,0,0,16,0,0,16,0,0,16,0,0,17,0,0,17,0,0,18,0,0,18,0,0,19,0,0,19,0,0,20,0,0,20,0,0,21,0,0,21,0,9,1,2,10,3,74],[0,0,0,0,0,0,0,0,0,0,0,0,0,0,0,0,0,0,0],[1,1,3,3,1,5,1,3,1,1,3,1,1,3,1,3,1,5,3],[10,11,0,0,1,1,12,0,2,13,0,2,14,0,2,0,1,1,0]]]]
